LICENSE
MANIFEST.in
README.md
setup.cfg
setup.py
src/os_spage/VERSION
src/os_spage/__init__.py
src/os_spage/common.py
src/os_spage/compat.py
src/os_spage/default_schema.py
src/os_spage/offpage_reader.py
src/os_spage/spage_reader.py
src/os_spage/spage_to_offpage.py
src/os_spage/spage_writer.py
src/os_spage/validator.py
src/os_spage.egg-info/PKG-INFO
src/os_spage.egg-info/SOURCES.txt
src/os_spage.egg-info/dependency_links.txt
src/os_spage.egg-info/not-zip-safe
src/os_spage.egg-info/requires.txt
src/os_spage.egg-info/top_level.txt
tests/__init__.py
tests/test_offpage_reader.py
tests/test_reader_and_writer.py
tests/test_validator.py